autoreview/__init__.py
autoreview/config.py
autoreview/core.py
autoreview/pipeline_autoreview.py
autoreview/spark_get_papers_2_degrees_out.py
autoreview/transformers.py
autoreview/util.py
autoreview/reanalysis/__init__.py
autoreview/reanalysis/collect_precision_recall.py
autoreview-0.2.5.dist-info/LICENSE
autoreview-0.2.5.dist-info/METADATA
autoreview-0.2.5.dist-info/WHEEL
autoreview-0.2.5.dist-info/top_level.txt
autoreview-0.2.5.dist-info/RECORD
