Metadata-Version: 2.1
Name: autoreview
Version: 0.2.5
Summary: Library for ranking relevant papers based on a set of seed papers
Home-page: https://github.com/h1-the-swan/autoreview
Author: Jason Portenoy
Author-email: jporteno@uw.edu
License: MIT
Platform: UNKNOWN
Requires-Dist: python-dotenv
Requires-Dist: pandas
Requires-Dist: numpy
Requires-Dist: sklearn
Requires-Dist: joblib
